AUTHORS.txt
LICENSE.txt
MANIFEST.in
README.md
setup.py
menpodetect/__init__.py
menpodetect/_static_version.py
menpodetect/_version.py
menpodetect/detect.py
menpodetect/paths.py
menpodetect.egg-info/PKG-INFO
menpodetect.egg-info/SOURCES.txt
menpodetect.egg-info/dependency_links.txt
menpodetect.egg-info/requires.txt
menpodetect.egg-info/top_level.txt
menpodetect/dlib/__init__.py
menpodetect/dlib/conversion.py
menpodetect/dlib/detect.py
menpodetect/dlib/train.py
menpodetect/models/opencv/haarcascade_eye.xml
menpodetect/models/opencv/haarcascade_frontalface_alt.xml
menpodetect/models/opencv/haarcascade_profileface.xml
menpodetect/opencv/__init__.py
menpodetect/opencv/conversion.py
menpodetect/opencv/detect.py
menpodetect/tests/__init__.py
menpodetect/tests/test_black.py
menpodetect/tests/test_detector.py
menpodetect/tests/test_dlib.py
menpodetect/tests/test_opencv.py